README.rst
setup.py
haxor_news/__init__.py
haxor_news/compat.py
haxor_news/completer.py
haxor_news/completions.py
haxor_news/config.py
haxor_news/hacker_news.py
haxor_news/hacker_news_cli.py
haxor_news/haxor.py
haxor_news/keys.py
haxor_news/main.py
haxor_news/main_cli.py
haxor_news/onions.py
haxor_news/settings.py
haxor_news/style.py
haxor_news/toolbar.py
haxor_news/utils.py
haxor_news/web_viewer.py
haxor_news.egg-info/PKG-INFO
haxor_news.egg-info/SOURCES.txt
haxor_news.egg-info/dependency_links.txt
haxor_news.egg-info/entry_points.txt
haxor_news.egg-info/requires.txt
haxor_news.egg-info/top_level.txt
haxor_news/lib/__init__.py
haxor_news/lib/debug_timer.py
haxor_news/lib/pretty_date_time.py
haxor_news/lib/haxor/__init__.py
haxor_news/lib/haxor/haxor.py
haxor_news/lib/haxor/settings.py
haxor_news/lib/html2text/__init__.py
haxor_news/lib/html2text/html2text.py
tests/__init__.py
tests/compat.py
tests/mock_hacker_news_api.py
tests/run_tests.py
tests/test_cli.py
tests/test_completer.py
tests/test_config.py
tests/test_hacker_news.py
tests/test_hacker_news_cli.py
tests/test_haxor.py
tests/test_keys.py
tests/test_toolbar.py
tests/data/__init__.py
tests/data/comment.py
tests/data/item.py
tests/data/markdown.py
tests/data/regex.py
tests/data/tip.py
tests/data/title.py
tests/data/url.py