Metadata-Version: 1.1
Name: haxor-news
Version: 0.4.3
Summary: View and filter Hacker News from the command line: Posts, comments, and linked web content.
Home-page: https://github.com/donnemartin/haxor-news
Author: Donne Martin
Author-email: donne.martin@gmail.com
License: Apache License 2.0
Download-URL: https://pypi.python.org/pypi/haxor-news
Platform: UNKNOWN
Classifier: Intended Audience :: Developers
Classifier: Intended Audience :: System Administrators
Classifier: License :: OSI Approved :: Apache Software License
Classifier: Natural Language :: English
Classifier: Programming Language :: Python
Classifier: Programming Language :: Python :: 2.6
Classifier: Programming Language :: Python :: 2.7
Classifier: Programming Language :: Python :: 3
Classifier: Programming Language :: Python :: 3.4
Classifier: Programming Language :: Python :: 3.5
Classifier: Topic :: Software Development
Classifier: Topic :: Software Development :: Libraries :: Python Modules
